tcpm/__init__.py
tcpm/__main__.py
tcpm/_core.py
tcpm/_data_model.py
tcpm/_errors.py
tcpm/_generators.py
tcpm/_pquery.py
tcpm/_rendering.py
tcpm/_utility.py
tcpm/py.typed
tcpm/version.py
tcpm/cli/__init__.py
tcpm/cli/_parser.py
tcpm-0.3.3.dist-info/entry_points.txt
tcpm-0.3.3.dist-info/licenses/LICENSE.rst
tcpm-0.3.3.dist-info/WHEEL
tcpm-0.3.3.dist-info/METADATA
tcpm-0.3.3.dist-info/RECORD
