Metadata-Version: 2.4
Name: tcpm
Version: 0.3.3
Summary: Generate CMakePresets.json configuration and build presets from the cartesian product of a set of parameters.
Author-email: Scott Dixon <dixonsco@amazon.com>
Requires-Python: >=3.10
Classifier: Development Status :: 3 - Alpha
Classifier: Intended Audience :: Developers
Classifier: License :: OSI Approved :: MIT License
Classifier: Programming Language :: Python :: 3 :: Only
Classifier: Programming Language :: Python :: 3.10
Classifier: Programming Language :: Python :: 3.11
Classifier: Programming Language :: Python :: 3.12
Classifier: Programming Language :: Python :: 3.13
License-File: LICENSE.rst
Requires-Dist: parsimonious
Requires-Dist: furo ; extra == "docs"
Requires-Dist: sphinx-argparse ; extra == "docs"
Requires-Dist: sphinxemoji ; extra == "docs"
Requires-Dist: sphinx ; extra == "docs"
Requires-Dist: jsonschema>=4.23.0 ; extra == "schema"
Requires-Dist: types-parsimonious ; extra == "test"
Requires-Dist: tox>=4.19.0 ; extra == "test"
Requires-Dist: black==25.1.0 ; extra == "test"
Requires-Dist: colorama ; extra == "test"
Requires-Dist: coverage ; extra == "test"
Requires-Dist: check-manifest==0.50 ; extra == "test"
Requires-Dist: flake8-bugbear ; extra == "test"
Requires-Dist: flake8-docstrings ; extra == "test"
Requires-Dist: flake8-formatter_junit_xml ; extra == "test"
Requires-Dist: flake8 ; extra == "test"
Requires-Dist: flake8-pyproject ; extra == "test"
Requires-Dist: isort==6.0.0 ; extra == "test"
Requires-Dist: lxml ; extra == "test"
Requires-Dist: mypy ; extra == "test"
Requires-Dist: pre-commit ; extra == "test"
Requires-Dist: pylint ; extra == "test"
Requires-Dist: pylint_junit ; extra == "test"
Requires-Dist: pytest-cov ; extra == "test"
Requires-Dist: pytest-mock ; extra == "test"
Requires-Dist: pytest-runner ; extra == "test"
Requires-Dist: pytest>=8.3.4 ; extra == "test"
Requires-Dist: pytest-github-actions-annotate-failures ; extra == "test"
Requires-Dist: sybil[pytest] ; extra == "test"
Requires-Dist: jsonschema>=4.23.0 ; extra == "test"
Project-URL: Documentation, https://thirtytwobits.github.io/the-cmake-preset-matrix
Project-URL: Source, https://github.com/thirtytwobits/the-cmake-preset-matrix
Project-URL: Tracker, https://github.com/thirtytwobits/the-cmake-preset-matrix/issues
Provides-Extra: docs
Provides-Extra: schema
Provides-Extra: test
